dhan16opm_libecl-0.1.5.dist-info/METADATA
dhan16opm_libecl-0.1.5.dist-info/RECORD
dhan16opm_libecl-0.1.5.dist-info/WHEEL
dhan16opm_libecl-0.1.5.dist-info/top_level.txt
ecl/__init__.py
ecl/ecl_type.py
ecl/ecl_util.py
ecl/libcatch2.dylib
ecl/libecl.2.3.dylib
ecl/libecl.2.dylib
ecl/libecl.dylib
ecl/eclfile/__init__.py
ecl/eclfile/ecl_3d_file.py
ecl/eclfile/ecl_3dkw.py
ecl/eclfile/ecl_file.py
ecl/eclfile/ecl_file_view.py
ecl/eclfile/ecl_init_file.py
ecl/eclfile/ecl_kw.py
ecl/eclfile/ecl_restart_file.py
ecl/eclfile/fortio.py
ecl/gravimetry/__init__.py
ecl/gravimetry/ecl_grav.py
ecl/gravimetry/ecl_grav_calc.py
ecl/gravimetry/ecl_subsidence.py
ecl/grid/__init__.py
ecl/grid/cell.py
ecl/grid/ecl_grid.py
ecl/grid/ecl_grid_generator.py
ecl/grid/ecl_region.py
ecl/grid/faults/__init__.py
ecl/grid/faults/fault.py
ecl/grid/faults/fault_block.py
ecl/grid/faults/fault_block_collection.py
ecl/grid/faults/fault_block_layer.py
ecl/grid/faults/fault_collection.py
ecl/grid/faults/fault_line.py
ecl/grid/faults/fault_segments.py
ecl/grid/faults/layer.py
ecl/rft/__init__.py
ecl/rft/ecl_rft.py
ecl/rft/ecl_rft_cell.py
ecl/rft/well_trajectory.py
ecl/summary/__init__.py
ecl/summary/ecl_cmp.py
ecl/summary/ecl_npv.py
ecl/summary/ecl_smspec_node.py
ecl/summary/ecl_sum.py
ecl/summary/ecl_sum_keyword_vector.py
ecl/summary/ecl_sum_node.py
ecl/summary/ecl_sum_tstep.py
ecl/summary/ecl_sum_var_type.py
ecl/summary/ecl_sum_vector.py
ecl/util/__init__.py
ecl/util/enums/__init__.py
ecl/util/enums/rng_alg_type_enum.py
ecl/util/enums/rng_init_mode_enum.py
ecl/util/geometry/__init__.py
ecl/util/geometry/cpolyline.py
ecl/util/geometry/cpolyline_collection.py
ecl/util/geometry/geo_pointset.py
ecl/util/geometry/geo_region.py
ecl/util/geometry/geometry_tools.py
ecl/util/geometry/polyline.py
ecl/util/geometry/surface.py
ecl/util/geometry/xyz_io.py
ecl/util/test/__init__.py
ecl/util/test/debug_msg.py
ecl/util/test/ert_test_context.py
ecl/util/test/ert_test_runner.py
ecl/util/test/extended_testcase.py
ecl/util/test/import_test_case.py
ecl/util/test/lint_test_case.py
ecl/util/test/path_context.py
