Metadata-Version: 2.1
Name: dhan16opm-libecl
Version: 0.1.5
Summary: libecl
Home-page: https://github.com/statoil/libecl
Author-email: chandan.nath@gmail.com
License: GNU General Public License, Version 3, 29 June 2007
Platform: UNKNOWN
Requires-Dist: cwrap
Requires-Dist: numpy
Requires-Dist: pandas
